README.txt
be
be.bat
setup.py
Bugs_Everywhere_BEurtle_fork_.egg-info/PKG-INFO
Bugs_Everywhere_BEurtle_fork_.egg-info/SOURCES.txt
Bugs_Everywhere_BEurtle_fork_.egg-info/dependency_links.txt
Bugs_Everywhere_BEurtle_fork_.egg-info/requires.txt
Bugs_Everywhere_BEurtle_fork_.egg-info/top_level.txt
libbe/__init__.py
libbe/_version.py
libbe/bug.py
libbe/bugdir.py
libbe/comment.py
libbe/diff.py
libbe/error.py
libbe/version.py
libbe/command/__init__.py
libbe/command/assign.py
libbe/command/base.py
libbe/command/comment.py
libbe/command/commit.py
libbe/command/depend.py
libbe/command/diff.py
libbe/command/due.py
libbe/command/help.py
libbe/command/html.py
libbe/command/import_xml.py
libbe/command/init.py
libbe/command/list.py
libbe/command/merge.py
libbe/command/new.py
libbe/command/remove.py
libbe/command/serve.py
libbe/command/set.py
libbe/command/severity.py
libbe/command/show.py
libbe/command/status.py
libbe/command/subscribe.py
libbe/command/tag.py
libbe/command/target.py
libbe/command/util.py
libbe/command/vcs.py
libbe/storage/__init__.py
libbe/storage/base.py
libbe/storage/http.py
libbe/storage/util/__init__.py
libbe/storage/util/config.py
libbe/storage/util/mapfile.py
libbe/storage/util/properties.py
libbe/storage/util/settings_object.py
libbe/storage/util/upgrade.py
libbe/storage/vcs/__init__.py
libbe/storage/vcs/arch.py
libbe/storage/vcs/base.py
libbe/storage/vcs/bzr.py
libbe/storage/vcs/darcs.py
libbe/storage/vcs/git.py
libbe/storage/vcs/hg.py
libbe/storage/vcs/monotone.py
libbe/ui/__init__.py
libbe/ui/command_line.py
libbe/ui/util/__init__.py
libbe/ui/util/editor.py
libbe/ui/util/pager.py
libbe/ui/util/user.py
libbe/util/__init__.py
libbe/util/encoding.py
libbe/util/id.py
libbe/util/plugin.py
libbe/util/subproc.py
libbe/util/tree.py
libbe/util/utility.py