Metadata-Version: 1.0
Name: Bugs-Everywhere-BEurtle-fork-
Version: 1.5.0.1.-2012-07-16-
Summary: Bugtracker supporting distributed revision control
Home-page: http://bugseverywhere.org/
Author: UNKNOWN
Author-email: UNKNOWN
License: UNKNOWN
Platform: UNKNOWN
